gsk_geo_encryption/__init__.py
gsk_geo_encryption/gsk_geo_encryption.py
gsk_geo_encryption-1.0.dist-info/METADATA
gsk_geo_encryption-1.0.dist-info/WHEEL
gsk_geo_encryption-1.0.dist-info/top_level.txt
gsk_geo_encryption-1.0.dist-info/RECORD
