Metadata-Version: 2.1
Name: gsk-geo-encryption
Version: 1.0
Summary: Geological Password Encryption
Home-page: UNKNOWN
Author: G S SRENATH KUMAR
License: UNKNOWN
Platform: UNKNOWN
